{
	"hello": "Hello",
	"welcome": "Welcome to our application",
	"height": "Height",
	"mass": "Mass ",
	"climate": "Climate",
	"population": "Population",
	"diameter": "Diameter",
	"gravity": "Gravity",
	"orbital_period": "Orbital Period",
	"rotation_period": "Rotation Period",
	"surface_water": "Surface Water",
	"terrain": "Terrain",
	"gender": "Gender",
	"hair_color": "Hair Color",
	"skin_color": "Skin Color",
	"eye_color": "Eye Color",
	"birth_year": "Birth Year",
	"release_date": "Release Date",
	"director": "Director",
	"episode_number": "Episode Number",
	"opening_crawl": "Opening Crawl",
	"search_placeholder_character": "Search a character",
	"search_placeholder_movie": "Search a movie",
	"search_placeholder_planet": "Search a planet",
	"search_placeholder_default": "Search...",
	"quiz": "Quiz",
	"characters": "Characters",
	"movies": "Movies",
	"planets": "Planets",
	"search_button": "Search",
	"footer_column_1_title": "Column 1",
	"footer_column_2_title": "Column 2",
	"footer_column_3_title": "Column 3",
	"footer_point_1": "Point 1",
	"footer_point_2": "Point 2",
	"footer_point_3": "Point 3",
	"footer_point_4": "Point 4",
	"footer_rights": "© {{year}} Omar Sherif. All rights reserved.",
	"characters_title": "Star Wars Characters",
	"characters_height": "Height: {{height}}",
	"characters_birth_year": "Birth Year: {{birthYear}}",
	"characters_gender": "Gender: {{gender}}",
	"characters_homeworld": "Homeworld: {{homeworld}}",
	"characters_prev_page": "Previous Page",
	"characters_next_page": "Next Page",
	"characters_unknown": "Unknown",
	"movies_title": "Star Wars Movies",
	"movies_release_date": "Release Date: {{releaseDate}}",
	"movies_director": "Director: {{director}}",
	"movies_producer": "Producer: {{producer}}",
	"movies_opening_crawl": "Opening Crawl: {{openingCrawl}}",
	"movies_more_info": "More Info",
	"movies_back_to_movies": "Back to Movies",
	"movies_unknown": "Unknown",
	"planets_title": "Star Wars Planets",
	"planets_population": "Population: {{population}}",
	"planets_terrain": "Terrain: {{terrain}}",
	"planets_surface_water": "Surface Water: {{surfaceWater}}",
	"planets_climate": "Climate: {{climate}}",
	"planets_gravity": "Gravity: {{gravity}}",
	"planets_more_info": "More Info",
	"planets_back_to_planets": "Back to Planets",
	"planets_previous_page": "Previous Page",
	"planets_next_page": "Next Page",
	"loading": "Loading...",
	"error": "Error: {{error}}"
}
